{
  "$schema": "https://developer.microsoft.com/json-schemas/fabric/item/report/definition/visualContainer/2.2.0/schema.json",
  "name": "eccec54523b7ff359d4f",
  "position": {
    "x": 151.18110236220471,
    "y": 285.73228346456693,
    "z": 8000,
    "height": 114.89763779527559,
    "width": 270.61417322834643,
    "tabOrder": 4000
  },
  "visual": {
    "visualType": "card",
    "query": {
      "queryState": {
        "Values": {
          "projections": [
            {
              "field": {
                "Measure": {
                  "Expression": {
                    "SourceRef": {
                      "Entity": "Medidas"
                    }
                  },
                  "Property": "SaldoHoras Devido Empresa"
                }
              },
              "queryRef": "Medidas.SaldoHoras Devido Empresa",
              "nativeQueryRef": "SaldoHoras Devido Empresa"
            }
          ]
        }
      },
      "sortDefinition": {
        "sort": [
          {
            "field": {
              "Measure": {
                "Expression": {
                  "SourceRef": {
                    "Entity": "Medidas"
                  }
                },
                "Property": "SaldoHoras Devido Empresa"
              }
            },
            "direction": "Descending"
          }
        ],
        "isDefaultSort": true
      }
    },
    "objects": {
      "categoryLabels": [
        {
          "properties": {
            "color": {
              "solid": {
                "color": {
                  "expr": {
                    "ThemeDataColor": {
                      "ColorId": 0,
                      "Percent": -0.3
                    }
                  }
                }
              }
            },
            "show": {
              "expr": {
                "Literal": {
                  "Value": "false"
                }
              }
            }
          }
        }
      ],
      "labels": [
        {
          "properties": {
            "color": {
              "solid": {
                "color": {
                  "expr": {
                    "Literal": {
                      "Value": "'#FF0000'"
                    }
                  }
                }
              }
            },
            "fontSize": {
              "expr": {
                "Literal": {
                  "Value": "30D"
                }
              }
            },
            "bold": {
              "expr": {
                "Literal": {
                  "Value": "true"
                }
              }
            },
            "labelDisplayUnits": {
              "expr": {
                "Literal": {
                  "Value": "1D"
                }
              }
            },
            "labelPrecision": {
              "expr": {
                "Literal": {
                  "Value": "0L"
                }
              }
            }
          }
        }
      ]
    },
    "visualContainerObjects": {
      "background": [
        {
          "properties": {
            "show": {
              "expr": {
                "Literal": {
                  "Value": "false"
                }
              }
            }
          }
        }
      ]
    },
    "drillFilterOtherVisuals": true
  },
  "filterConfig": {
    "filters": [
      {
        "name": "02feecb62242e65bded4",
        "field": {
          "Column": {
            "Expression": {
              "SourceRef": {
                "Entity": "fact_Colaboradores"
              }
            },
            "Property": "DIRETORIA"
          }
        },
        "type": "Categorical",
        "howCreated": "User"
      }
    ]
  }
}